numerax/__init__.py
numerax/utils.py
numerax/special/__init__.py
numerax/special/_erf_and_fresnel.py
numerax/special/_gamma.py
numerax/stats/__init__.py
numerax/stats/_profile.py
numerax/stats/chi2.py
numerax-1.2.0.dist-info/METADATA
numerax-1.2.0.dist-info/WHEEL
numerax-1.2.0.dist-info/licenses/LICENSE
numerax-1.2.0.dist-info/RECORD
