Metadata-Version: 2.4
Name: numerax
Version: 1.2.0
Project-URL: Documentation, https://juehang.github.io/numerax/
Project-URL: Issues, https://github.com/juehang/numerax/issues
Project-URL: Source, https://github.com/juehang/numerax
Author: Juehang Qin
License-Expression: MIT
License-File: LICENSE
Classifier: Development Status :: 4 - Beta
Classifier: Programming Language :: Python
Classifier: Programming Language :: Python :: 3.11
Classifier: Programming Language :: Python :: 3.12
Classifier: Programming Language :: Python :: 3.13
Classifier: Programming Language :: Python :: 3.14
Classifier: Programming Language :: Python :: 3.15
Classifier: Programming Language :: Python :: Implementation :: CPython
Classifier: Programming Language :: Python :: Implementation :: PyPy
Requires-Python: >=3.11
Requires-Dist: jax
Requires-Dist: jaxtyping
Requires-Dist: optax
Provides-Extra: sciml
Requires-Dist: equinox; extra == 'sciml'
